["{\"slug\":\"askcarsales\",\"over18\":0,\"public_description\":\"A place to ask questions from car sales professionals - sales people, finance and sales managers. Please note that verified professionals will have flair, take advice from non-flaired users with discretion.\\n\\nBring back \\\/u\\\/chooter\",\"title\":\"Ask a Car Salesman, Managers, or Finance managers anything!\",\"header_title\":\"http:\\\/\\\/imgur.com\\\/05AgvE0\",\"flairstring\":\"Canadian Sale\\u001fUS Sale\\u001fEuropean Sale\\u001fMeta\\u001fMod Post\\u001fPrivate Sale\\u001fAustrailian Sale\\u001fUS Purchase\\u001fCanadian Sale - Buy here pay here\\u001fUS Sale\\\/Trade Maryland\\u001fUS Sale decision \\u001fUS Lease\\u001fYoutube\\u001fHelp\\u001fHelp Wanted US\\u001fUS Private Sale\\u001fAustralian Sale\\u001fUS SALE\\u001fMechanic He\",\"subscribers\":\"15,208\",\"hot_rank\":1698,\"subs_rank\":2688,\"growth_rank\":4170}"]