["{\"slug\":\"Astros\",\"over18\":0,\"public_description\":\"Home of the MLB Houston Astros\",\"title\":\"There are literally dozens of us! Dozens!\",\"header_title\":\"There are literally dozens of us! Dozens!\",\"flairstring\":\"Pic\\u001fLow Quality\\u001fLost\\u001fGDT\\u001fMisc\\u001fWon\\u001fNews\\u001fDiscussion\\u001fVideo\\u001fQuestion\\u001fFluff\\u001fCircle Jerk\\u001fOfficial\\u001fWin\\u001fMeta\\u001fGame\\u001fMeetup!!!\",\"subscribers\":\"6,352\",\"hot_rank\":1166,\"subs_rank\":3917,\"growth_rank\":3470}"]