["{\"slug\":\"BBW_Chubby\",\"over18\":1,\"public_description\":\"THEBBWGF --&gt; Fat and Chubby Ex Girlfriends caught on cam!\\n\\nThe Community for the BBW-Chubby Lovers. \\n\\n\\nPlease no Spam or hateful comments.\\n\\nPlease post only if you love Chubby Girls!\",\"title\":\"BBW and Chubby Ex Girlfriends\",\"header_title\":\"TheBBWGF.com ----- Fat and Chubby Ex Girlfriends caught on cam!\",\"flairstring\":\"\",\"subscribers\":\"3,894\",\"hot_rank\":4160,\"subs_rank\":4377,\"growth_rank\":288}"]