["{\"slug\":\"Borderlands\",\"over18\":0,\"public_description\":\"A subreddit specifically for the game Borderlands, including all DLC, sequels, pre-sequels, and re-pre-sequels.\",\"title\":\"Borderlands\",\"header_title\":\"Hello, traveler!\",\"flairstring\":\"[BL1]\\u001f[BL3]\\u001f[BL2]\\u001fXBOX360\\u001fSteam\\u001fPS3\\u001fTFTB\\u001f[BL: TFTBL]\\u001f[BL: TPS]\\u001fTales Of The Borderlands\\u001fPC BL2\\u001f[BL]\\u001f[BL: TFTBL] [SPOILERS]\\u001f[SPOILERS]\\u001fPS4\\u001fPC\\u001fYeezy Breezy Beautiful\\u001fXB1\\u001fKrieg's Mind is on fire!\\u001f[BL2] PC\\u001f[BL1] solved\\u001fQuestion\\\/Problem\\u001fPSVITA\\u001f[BL: TPS Steam]\\u001f\",\"subscribers\":\"67,491\",\"hot_rank\":1625,\"subs_rank\":776,\"growth_rank\":4348}"]