["{\"slug\":\"CK2GameOfthrones\",\"over18\":0,\"public_description\":\"This is the subreddit for those who play the Game of Thrones mod for the game Crusader Kings 2. \",\"title\":\"The subreddit for people who play the Game Of Thrones Mod in Crusader Kings 2 \",\"header_title\":\"\",\"flairstring\":\"[MOD POST]\\u001f[Spoilers ACOK]\\u001f[No Spoilers]\\u001f[Weekly Challenge]\\u001f[Spoilers All]\\u001f[Spoilers AFFC]\\u001fSuccession Game\\u001f[Advertisement]\\u001f[Multiplayer Ad]\\u001f[Sub Mod]\\u001f[Mod Post]\\u001f[Moderator Approved]\\u001f[Mod Approved]\\u001f[Bi-Weekly Challenge]\\u001f[Dicks Out][No Spoilers]\",\"subscribers\":\"9,371\",\"hot_rank\":2700,\"subs_rank\":3396,\"growth_rank\":1589}"]