["{\"slug\":\"customhearthstone\",\"over18\":0,\"public_description\":\"Welcome to \\\/r\\\/CustomHearthstone\\n\\nThis is a place to share and discuss your cards and ideas for Hearthstone. We're home to a growing community and weekly card design competitions. If you love Hearthstone and game design, you've come to the right place!\\n\",\"title\":\"Custom Hearthstone\",\"header_title\":\"Back to reddit front page.\",\"flairstring\":\"Card\\u001fSet\\u001fExpansion\\u001fClass\\u001fDiscussion\\u001fMechanic\\u001fCompetition\\u001fAnnouncement\",\"subscribers\":\"12,889\",\"hot_rank\":632,\"subs_rank\":2936,\"growth_rank\":1126}"]