["{\"slug\":\"datbuttfromthefront\",\"over18\":1,\"public_description\":\"It\\u2019s that thing when she\\u2019s got her legs spread so that her cheeks are show slightly from underneath, and the tendons on her inner thighs protrude.  It\\u2019s not quite the gap.  It\\u2019s not quite spread eagle, although that\\u2019s close.  There really isn't a word for it, but we call it **Dat Butt From the Front**!\",\"title\":\"Dat Butt From the Front\",\"header_title\":\"\",\"flairstring\":\"GOOD SHIT\\u001fDBFTF GW\",\"subscribers\":\"18,856\",\"hot_rank\":3938,\"subs_rank\":2338,\"growth_rank\":732}"]