["{\"slug\":\"DNCleaks\",\"over18\":0,\"public_description\":\"https:\\\/\\\/wikileaks.org\\\/dnc-emails\\\/\\n\\nThis subreddit was created to post details and significant finds from the DNC leak in a more organized, central area.    \\n  \\nKeywords: DNC, leaks, wikileaks, Hillary, Clinton, Sanders, DWS, guccifer, hack, data, email, politics, news, leak, DNCLeak\",\"title\":\"DNCLeaks\",\"header_title\":\"\",\"flairstring\":\"News Story\\u001fE-Mail Link\\u001fMod Post\\u001fIMPORTANT\\u001fSelf\\u001fSocial Media Link\\u001fOff-Topic\\u001fWiki\\u001fVerified\\u001fAMA starts at 12 pm\\u001fMod note: Guccifer hacks not DNC Leaks\\u001fMod note: Guccifer hacks are not DNC Leaks.\",\"subscribers\":\"10,151\",\"hot_rank\":787,\"subs_rank\":3290,\"growth_rank\":522}"]