["{\"slug\":\"Frat\",\"over18\":0,\"public_description\":\"Because reddit is the anti-frat\",\"title\":\"Frat\",\"header_title\":\"\",\"flairstring\":\"Do Not Participate\\u001fVerified \\u001fNews Story\\u001fShameless Plug\\u001fQuestion\\u001fSatire\\u001fDank Meme\\u001fMegathread\\u001fHumor\\u001fMegathread?\\u001fSerious\\u001fTriggered\\u001fr\\\/relationships\\u001fFrat Stuff\\u001fHumor?\\u001fQuestion?\\u001fSatire maybe idk\\u001f'Murica\\u001fThey Drink\\u001fWitch Hunt?\\u001f?\\u001fInformation\\u001fSuggestion\\u001flow effort\",\"subscribers\":\"14,997\",\"hot_rank\":748,\"subs_rank\":2716,\"growth_rank\":1213}"]