["{\"slug\":\"Frisson\",\"over18\":0,\"public_description\":\"\",\"title\":\"Frisson\",\"header_title\":\"frisson: an emotional &amp; physical reaction resulting in goosebumps, chills, or a shudder\",\"flairstring\":\"Image\\u001fMusic\\u001fVideo\\u001fText\\u001fMod Post\\u001fInteractive\\u001fAudio\\u001fComic\\u001fThought\\u001fMeta\\u001fIllustration\\u001fVideo-Spoilers\\u001fRemoved - Ambiguous title\",\"subscribers\":\"124,061\",\"hot_rank\":1055,\"subs_rank\":413,\"growth_rank\":2742}"]