["{\"slug\":\"gaypornhunters\",\"over18\":1,\"public_description\":\"Looking for a Japanese twink getting railed by two hunky latino men in a hot tub? Trying to figure out the name of the man getting rimmed in a photo you saved four years ago? Need proof that triple penetration is indeed possible? Look no further: leave it up to the Gay Porn Hunters!\\n\\n\",\"title\":\"Gay Porn Hunters\",\"header_title\":\"You've Cum To The Right Place\",\"flairstring\":\"[FOUND]\\u001f[DEAD LINK]\",\"subscribers\":\"11,931\",\"hot_rank\":3191,\"subs_rank\":3055,\"growth_rank\":1385}",["gay","men"]]