["{\"slug\":\"MandelaEffect\",\"over18\":0,\"public_description\":\"Do you remember certain personal or world events happening differently than they did for everyone else?\\n\",\"title\":\"The Mandela Effect\",\"header_title\":\"\",\"flairstring\":\"Meta\\u001fMass Media\\u001fBible \\\/ Religon\\u001fGeography\\u001fLogos\\u001fNews Reports\\u001fPersonal Experience\\u001fName Changes\\u001fFamous People\\u001fBerenstain Bears\\u001fMusic\\u001fStar Wars\\u001fMeta?\\u001fSOLVED\",\"subscribers\":\"21,837\",\"hot_rank\":892,\"subs_rank\":2133,\"growth_rank\":290}"]