["{\"slug\":\"masseffect\",\"over18\":0,\"public_description\":\"This subreddit is for people who love the Mass Effect universe - the games, the books, the comics and even the DLC. As awesome as BioWare is, please keep the discussion generally limited to the Mass Effect universe.\",\"title\":\"For lovers of the Mass Effect universe.\",\"header_title\":\"Friendly: Human, delighted welcome\",\"flairstring\":\"Fan art\\u001fQuestion\\u001fOfficial\\u001fDiscussion\\u001fArticle\\u001fVideo\\u001fRumor\\u001fMass Effect 2\\u001fSpoilers\\u001fMass Effect 1\\u001fMass Effect 3\\u001fMass Effect Andromeda\\u001fFan Art\\u001fPlease don't give me any spoilers\\u001fVideo |\\u001fMass Effect 3 |\\u001fMass Effect 1 |\\u001fMass Effect 2 |\\u001fSpoilers Mass Effect 2\\u001fSash\",\"subscribers\":\"96,930\",\"hot_rank\":399,\"subs_rank\":541,\"growth_rank\":2965}"]