["{\"slug\":\"Mcat\",\"over18\":0,\"public_description\":\"MCAT subreddit is the place for the discussion, stress support, social networking, and news for the AAMC MCAT exam where registered premedical students can submit content, such as text posts or direct links. \\n\",\"title\":\"MCAT: Help and Discussion\",\"header_title\":\"\",\"flairstring\":\"Study question\\u001fSPOILER\\u001fRIP Flashcard Guy\\u001fAAMC HATES HIM\\u001fAAMC Flashcards\\u001fStudy Help\\\/Tips\\u001fStudy Help\\u001fSPOILER: S\\\/B C\\\/P\\u001fStudy Tips\\u001fMOD News\\u001fSPOILER: S\\\/B B\\\/B\\u001fSPOILER: S\\\/B P\\\/S\\u001fContent Q: P\\\/S\\u001fSPOIL:AAMCSample\\u001fContent Help\\\/Tips\\u001f\\u0f3c \\u3064 \\u25d5_\\u25d5 \\u0f3d\\u3064\\u001fSPOIL:AAMCFLScored\",\"subscribers\":\"6,124\",\"hot_rank\":1997,\"subs_rank\":3953,\"growth_rank\":384}"]