["{\"slug\":\"montreal\",\"over18\":0,\"public_description\":\"A community for Montreal and its loving residents. We speak French too!\\n\\nUne communaut\\u00e9 pour Montr\\u00e9al et ses r\\u00e9sidents bien aim\\u00e9s. On parle anglais aussi!\",\"title\":\"Montr\\u00e9al\",\"header_title\":\"aweille Denis\",\"flairstring\":\"Updated: Quits politics\\u001fUpdated: 42M$\\u001fFire\\u001fExpos \\\/ Baseball\\u001fRant\\u001fNot inside the market\\u001fFreedom Friday\\u001fWhere in MTL?\\u001fNews\\u001fSports\\u001fTourist question\\u001fUpdate\\u001fHistorical\\u001fLegal\\u001fTourism\\u001fCulture\\u001fRestaurant\\u001fTechnology\\u001fFood\\u001fGr\\u00e8ve \\u00c9tudiante\\u001fHousing\\u001fWrong sub\\u001fEvent\\u001fMet\",\"subscribers\":\"26,126\",\"hot_rank\":1212,\"subs_rank\":1855,\"growth_rank\":3509}"]