["{\"slug\":\"nba\",\"over18\":0,\"public_description\":\"All things NBA basketball.\",\"title\":\"NBA\",\"header_title\":\"\",\"flairstring\":\"National Writer\\u001fSpoilers\\u001fHighlights\\u001fNews\\u001fBeat Writer\\u001fMisc. Media\\u001fGame Thread\\u001fAnalysis\\u001fRoster Moves\\u001f\\\/r\\\/NBA OC\\u001fStats\\u001fFalse Information\\u001fTRASH TALK\\u001fMisleading\\u001fTANK TALK\\u001fConfirmed\\u001fAnnouncements\\u001fTeam Blog\\u001fOfficial Post Game\\u001f**MUST READ**\\u001fModpost\\u001fPost Game Threa\",\"subscribers\":\"432,431\",\"hot_rank\":24,\"subs_rank\":100,\"growth_rank\":2770}",["culture","discussion","info","sports"]]