["{\"slug\":\"Rockband\",\"over18\":0,\"public_description\":\"A subreddit for all things Rock Band.\",\"title\":\"Rock Band: because everyone wants to rock.\",\"header_title\":\"A place for all things Rock Band\",\"flairstring\":\"Announcement\\u001fPSA\\u001fSale\\u001fOffline\\u001fXB1 downloads up\\u001fOut on PS4\\\/XB1!\\u001fOut on XB1\\u001fAvailable now!\\u001fOut now on XB1\\u001fDelayed in Europe\\u001fVideo\\u001fNow available!\\u001fNow Available!\\u001fDelayed\\u001fVideo in comments\\u001fExport News\\u001fHumor\\u001fSCEA PS4\\u001fSong delay [SCEA]\",\"subscribers\":\"10,212\",\"hot_rank\":2578,\"subs_rank\":3281,\"growth_rank\":3426}"]