["{\"slug\":\"sciencefiction\",\"over18\":0,\"public_description\":\"This reddit is for fans and creators of Science Fiction and related media in any form. SF topics should involve plausible ideas reached through the rational application of science.  General speculative fiction posts are fine as long as they involve Science Fiction.\\n\",\"title\":\"Science Fiction\",\"header_title\":\"design by kjhatch\",\"flairstring\":\"\",\"subscribers\":\"35,195\",\"hot_rank\":2438,\"subs_rank\":1444,\"growth_rank\":3447}"]