["{\"slug\":\"serialpodcast\",\"over18\":0,\"public_description\":\"Serial is a podcast by the creators of This American Life. Each season explores a nonfictional story in weekly installments.\\n\\nThis subreddit is a place to discuss your theories, predictions and other aspects of the show.\",\"title\":\"A place to discuss Serial: The Podcast\",\"header_title\":\"Snoo Koenig\",\"flairstring\":\"Modern Jackass\\u001fDebate&amp;Discussion\\u001fQuestion\\u001fRelated Media\\u001fEvidence\\u001fSpeculation\\u001fMeta\\u001fHumor\\\/Off Topic\\u001fLegal News&amp;Views\\u001fHypothesis\\u001fTranscript\\u001fOfficial SERIAL\\u001fPoll\\u001fCriminology\\u001fMisleading\\u001fEpisode Discussion\\u001fDistantly Related Media\\u001fNoteworthy Link\\u001fDonate \",\"subscribers\":\"51,727\",\"hot_rank\":1245,\"subs_rank\":1007,\"growth_rank\":4211}"]