["{\"slug\":\"theocho\",\"over18\":0,\"public_description\":\"Grab life by the balls. \\n\\nThe ocho is for obscure sports\",\"title\":\"The Ocho: if it's almost a sport, we've got it here\",\"header_title\":\"\",\"flairstring\":\"ANIMALS\\u001fWINTER\\u001fMOTORS\\u001fFUN AND GAMES\\u001fEXTREME\\u001fCRAFT\\u001f???\\u001fOCHO APPROVED\\u001fPARODY\\u001fSPORTS MASHUP\\u001fMETA\\u001fJAPANESE GAMESHOW\\u001fJAPAN\\u001fOUTDOORS\\u001fONE-OFF\\u001f\\\/r\\\/BUGWARS\\u001fHEADIS\\u001fROUTINE\\u001fHE DID IT!\\u001f\\\/r\\\/THROWERS\\u001f\\\/r\\\/AFL\\u001f\\\/r\\\/HANDBALL\\u001f\\\/r\\\/PAINTBALL\\u001fWELP.\\u001fWE DID IT AMERICA\\u001f\\\/r\\\/HOLDMYREDBUL\",\"subscribers\":\"81,374\",\"hot_rank\":1730,\"subs_rank\":642,\"growth_rank\":3479}"]