["{\"slug\":\"WesternHentai\",\"over18\":1,\"public_description\":\"This subreddit is for the more western erotic art. X-rated art like the kind you might see in a Disney film or a batman comic for instance.\\n\\n* Example of western art: [Here](http:\\\/\\\/i.imgur.com\\\/R8rADBd.jpg)\\n\\n* Example of classic hentai: [Here](http:\\\/\\\/i.imgur.com\\\/LXc10YI.jpg)\",\"title\":\"Western Hentai\",\"header_title\":\"\",\"flairstring\":\"\",\"subscribers\":\"28,074\",\"hot_rank\":3643,\"subs_rank\":1752,\"growth_rank\":2382}"]