["{\"slug\":\"winnipegjets\",\"over18\":0,\"public_description\":\"A subreddit dedicated to the Winnipeg Jets of the NHL.\",\"title\":\"Winnipeg Jets\",\"header_title\":\"Praise be to the Chevy, the Maurice, and the Holy True North\",\"flairstring\":\"Discussion\\u001fWrite-ins accepted\\u001fConnor \\\/ Kariya\\u001fDetails Inside\\u001fLittle out for season with compression fracture of T6 vertebrae\\u001fLipon recalled\\u001fArmia injured\\u001fConnor\\u001fGame in WPG\\u001fApril 6\\u001f3 yrs \\\/ 1.775m AAV\\u001fRumor\\u001f2 yrs \\\/ 2.125M AAV\\u001f$4.125M AAV\",\"subscribers\":\"3,503\",\"hot_rank\":3736,\"subs_rank\":4446,\"growth_rank\":4417}"]